LICENSE.txt
MANIFEST.in
README.md
setup.py
cmsplugin_simpleslider/__init__.py
cmsplugin_simpleslider/admin.py
cmsplugin_simpleslider/cms_plugins.py
cmsplugin_simpleslider/models.py
cmsplugin_simpleslider/settings.py
cmsplugin_simpleslider/tests.py
cmsplugin_simpleslider.egg-info/PKG-INFO
cmsplugin_simpleslider.egg-info/SOURCES.txt
cmsplugin_simpleslider.egg-info/dependency_links.txt
cmsplugin_simpleslider.egg-info/requires.txt
cmsplugin_simpleslider.egg-info/top_level.txt
cmsplugin_simpleslider/locale/de/LC_MESSAGES/django.mo
cmsplugin_simpleslider/locale/de/LC_MESSAGES/django.po
cmsplugin_simpleslider/migrations/0001_initial.py
cmsplugin_simpleslider/migrations/0002_auto_20150730_0853.py
cmsplugin_simpleslider/migrations/__init__.py
cmsplugin_simpleslider/static/cmsplugin_simpleslider/bower_components/jquery/dist/jquery.js
cmsplugin_simpleslider/static/cmsplugin_simpleslider/bower_components/jquery/dist/jquery.min.js
cmsplugin_simpleslider/static/cmsplugin_simpleslider/bower_components/jquery/dist/jquery.min.map
cmsplugin_simpleslider/static/cmsplugin_simpleslider/bower_components/jquery/src/ajax.js
cmsplugin_simpleslider/static/cmsplugin_simpleslider/bower_components/jquery/src/attributes.js
cmsplugin_simpleslider/static/cmsplugin_simpleslider/bower_components/jquery/src/callbacks.js
cmsplugin_simpleslider/static/cmsplugin_simpleslider/bower_components/jquery/src/core.js
cmsplugin_simpleslider/static/cmsplugin_simpleslider/bower_components/jquery/src/css.js
cmsplugin_simpleslider/static/cmsplugin_simpleslider/bower_components/jquery/src/data.js
cmsplugin_simpleslider/static/cmsplugin_simpleslider/bower_components/jquery/src/deferred.js
cmsplugin_simpleslider/static/cmsplugin_simpleslider/bower_components/jquery/src/deprecated.js
cmsplugin_simpleslider/static/cmsplugin_simpleslider/bower_components/jquery/src/dimensions.js
cmsplugin_simpleslider/static/cmsplugin_simpleslider/bower_components/jquery/src/effects.js
cmsplugin_simpleslider/static/cmsplugin_simpleslider/bower_components/jquery/src/event.js
cmsplugin_simpleslider/static/cmsplugin_simpleslider/bower_components/jquery/src/intro.js
cmsplugin_simpleslider/static/cmsplugin_simpleslider/bower_components/jquery/src/jquery.js
