Metadata-Version: 1.1
Name: cmsplugin-simpleslider
Version: 0.1.0b5
Summary: A djangocms carousel slider plugin.
Home-page: https://github.com/creimers/cmsplugin_simpleslider
Author: Christoph Reimers
Author-email: christoph@superservice-international.com
License: BSD License
Keywords: djangocms,django,carousel,slider
Platform: UNKNOWN
Classifier: Operating System :: OS Independent
Classifier: Development Status :: 4 - Beta
Classifier: Programming Language :: Python
Classifier: Framework :: Django
Classifier: Programming Language :: Python :: 2.7
Classifier: Programming Language :: Python :: 3.4
